bench_it-1.0.1.dist-info/DESCRIPTION.rst
bench_it-1.0.1.dist-info/METADATA
bench_it-1.0.1.dist-info/RECORD
bench_it-1.0.1.dist-info/WHEEL
bench_it-1.0.1.dist-info/metadata.json
bench_it-1.0.1.dist-info/top_level.txt
benchit/__init__.py
benchit/benchit.py
benchit/prettytable.py
tests/__init__.py
tests/context.py
tests/test_benchit.py
