Metadata-Version: 2.0
Name: bench-it
Version: 1.0.1
Summary: Quick and easy python benchmarking.
Home-page: http://github.com/scuml/benchit
Author: Stephen Mitchell
Author-email: stephen@echodot.com
License: Copyright 2016-2018 Stephen Mitchell
